Part3_Integration/cpu.v
`include "alu.v"
`include "reg.v"

module cpu(PC, INSTRUCTION, CLK, RESET);

    // Input Port Declaration
    input [31:0] INSTRUCTION;
    input CLK, RESET;

    // Output Port Declaration
    output reg [31:0] PC;

    // Connections for Register File
    wire [2:0] READREG1, READREG2, WRITEREG;
    wire [7:0] REGOUT1, REGOUT2;
    reg WRITEENABLE;

    // Connections for ALU
    wire [7:0] OPERAND1, OPERAND2, ALURESULT;
    reg [2:0] ALUOP;

    // Connections for negation MUX
    wire [7:0] negatedOp;
    wire [7:0] registerOp;
    reg signSelect;

    // Connections for immediate value MUX
    wire [7:0] IMMEDIATE;
    reg immSelect;

    // PC value stored inside CPU
    reg [31:0] PCreg;

    // Current OPCODE stored in CPU
    reg [7:0] OPCODE;

    // Instantiation of CPU modules
    reg_file my_reg(ALURESULT, REGOUT1, REGOUT2, WRITEREG, READREG1, READREG2, WRITEENABLE, CLK, RESET);

    alu my_alu(REGOUT1, OPERAND2, ALURESULT, ALUOP);

    twosComp my_twosComp(REGOUT2, negatedOp);

    mux negationMUX(REGOUT2, negatedOp, signSelect, registerOp);

    mux immediateMUX(registerOp, IMMEDIATE, immSelect, OPERAND2);

    //PC - Program counter

    always @ ( posedge CLK)
	begin
		if (RESET == 1'b1) 
		begin
			#1
			PC = 0;		//If RESET signal is HIGH, set PC to zero
			PCreg = 0;
		end
		else #1 PC = PCreg;		//Else, write new PC value
	end
	
	
	//PC+4 Adder
	always @ (PC)
	begin
		#1 PCreg = PCreg + 4;
	end

    	//Relevant portions of INSTRUCTION are mapped to the respective units
	
	///////////////////////////////////////////////////////////////////
	/*    OP-CODE    /      RD       /       RT      /     RS/IMM    */
	/*    [31:24]    /    [23:16]    /     [15:8]    /      [7:0]    */
	///////////////////////////////////////////////////////////////////
	/*       |       /        |      /        |      /       |       */
	/*    OPCODE     /    WRITEREG   /    READREG1   /    READREG2   */
	/*               /               /               /   IMMEDIATE   */
	/*****************************************************************/
	assign READREG1 = INSTRUCTION[15:8];
	assign IMMEDIATE = INSTRUCTION[7:0];
	assign READREG2 = INSTRUCTION[7:0];
	assign WRITEREG = INSTRUCTION[23:16];

    	//Decoding the instruction
	always @ (INSTRUCTION)
	begin
	
		OPCODE = INSTRUCTION[31:24];	//Mapping the OP-CODE section of the instruction to OPCODE
		
		#1			//1 Time Unit Delay for Decoding process
		
		case (OPCODE)
		
			//loadi instruction
			8'b00000000:	begin
								ALUOP = 3'b000;			//Set ALU to forward
								immSelect = 1'b1;		//Set MUX to select immediate value
								signSelect = 1'b0;		//Set sign select MUX to positive sign
								WRITEENABLE = 1'b1;		//Enable writing to register
							end
		
			//mov instruction
			8'b00000001:	begin
								ALUOP = 3'b000;			//Set ALU to FORWARD
								immSelect = 1'b0;		//Set MUX to select register input
								signSelect = 1'b0;		//Set sign select MUX to positive sign
								WRITEENABLE = 1'b1;		//Enable writing to register
							end
			
			//add instruction
			8'b00000010:	begin
								ALUOP = 3'b001;			//Set ALU to ADD
								immSelect = 1'b0;		//Set MUX to select register input
								signSelect = 1'b0;		//Set sign select MUX to positive sign
								WRITEENABLE = 1'b1;		//Enable writing to register
							end	
		
			//sub instruction
			8'b00000011:	begin
								ALUOP = 3'b001;			//Set ALU to ADD
								immSelect = 1'b0;		//Set MUX to select register input
								signSelect = 1'b1;		//Set sign select MUX to negative sign
								WRITEENABLE = 1'b1;		//Enable writing to register
							end

			//and instruction
			8'b00000100:	begin
								ALUOP = 3'b010;			//Set ALU to AND
								immSelect = 1'b0;		//Set MUX to select register input
								signSelect = 1'b0;		//Set sign select MUX to positive sign
								WRITEENABLE = 1'b1;		//Enable writing to register
							end
							
			//or operation
			8'b00000101:	begin
								ALUOP = 3'b011;			//Set ALU to OR
								immSelect = 1'b0;		//Set MUX to select register input
								signSelect = 1'b0;		//Set sign select MUX to positive sign
								WRITEENABLE = 1'b1;		//Enable writing to register
							end

		endcase
		
	end

endmodule



//modules 

module twosComp(IN, OUT);
    input [7:0] IN;
    output [7:0] OUT;

    // Combinational logic to assign two's complement value of input to output
    assign #1 OUT = ~IN + 1;
endmodule

module mux(IN1, IN2, SELECT, OUT);
    input [7:0] IN1, IN2;
    input SELECT;
    output reg [7:0] OUT;

    // MUX should update output value upon change of any of the inputs
    always @ (IN1, IN2, SELECT) begin
        if (SELECT == 1'b1) begin  // If SELECT is HIGH, switch to 2nd input
            OUT = IN2;
        end else begin              // If SELECT is LOW, switch to 1st input
            OUT = IN1;
        end
    end
endmodule

Part3_Integration/forward/forward.v
module forwardModule(
    DATA1, // 8-bit input
    DATA2, // 8-bit input
    forwardResult // 8-bit output
);
    input [7:0] DATA1, DATA2; // 8-bit inputs
    output reg [7:0] forwardResult; // 8-bit output

    always @(DATA1, DATA2) begin // trigger on changes to DATA1 or DATA2
        #1 forwardResult = DATA2; // Forward DATA2
    end
endmodule

Part1_ALU/or/or.v
module orModule (
    DATA1, // 8-bit input
    DATA2, // 8-bit input
    orResult // 8-bit output
);
    input [7:0] DATA1, DATA2; // 8-bit inputs
    output reg [7:0] orResult; // 8-bit output

    always @(DATA1, DATA2) begin // trigger on changes to DATA1 or DATA2
        #1 orResult = DATA1 | DATA2; // perform bitwise OR operation
    end
endmodule

Part1_ALU/and/and.v
module andModule (
    DATA1, // 8-bit input
    DATA2, // 8-bit input
    andResult // 8-bit output
);
    input [7:0] DATA1, DATA2; // 8-bit inputs
    output reg [7:0] andResult; // 8-bit output

    always @(DATA1, DATA2) begin // trigger on changes to DATA1 or DATA2
        #1 andResult = DATA1 & DATA2; // perform bitwise AND operation
    end
    
endmodule

Part3_Integration/add/add.v
module addModule ( DATA1, DATA2, addResult);
    input [7:0] DATA1,DATA2; // 8-bit inputs
    output reg [7:0] addResult; // 8-bit output

    always @(DATA1,DATA2) begin // trigger on changes to DATA1 or DATA2
        #2 addResult = DATA1 + DATA2;
    end

endmodule

Part3_Integration/alu.v
`include "add/add.v"
`include "and/and.v"
`include "or/or.v"
`include "forward/forward.v"

module alu(DATA1, DATA2, RESULT, SELECT);
    input [7:0] DATA1, DATA2; // 8-bit inputs
    input [2:0] SELECT; // 3-bit select input
    output reg [7:0] RESULT; // 8-bit output

    wire [7:0] addResult, andResult, orResult, forwardResult;

    // Instantiate the modules
    addModule addModuleAlu (
        .DATA1(DATA1),
        .DATA2(DATA2),
        .addResult(addResult)
    );
    andModule andModuleAlu (
        .DATA1(DATA1),
        .DATA2(DATA2),
        .andResult(andResult)
    );
    orModule orModuleAlu (
        .DATA1(DATA1),
        .DATA2(DATA2),
        .orResult(orResult)
    );
    forwardModule forwardModuleAlu (
        .DATA1(DATA1),
        .DATA2(DATA2),
        .forwardResult(forwardResult)
    );

    always @(addResult, andResult, orResult, forwardResult, SELECT) begin
        case (SELECT)
            3'b000: RESULT = forwardResult; // Forward
            3'b001: RESULT = addResult; // Add
            3'b010: RESULT = andResult; // AND
            3'b011: RESULT = orResult; // OR
        endcase
    end
endmodule

Part3_Integration/reg.v
module reg_file (
    IN,OUT1,OUT2,INADDRESS,OUT1ADDRESS,OUT2ADDRESS, WRITE, CLK, RESET
);
    input [7:0] IN;
    input [2:0] INADDRESS, OUT1ADDRESS, OUT2ADDRESS;
    input WRITE, CLK, RESET;
    output [7:0] OUT1, OUT2;

    reg [7:0] registers [7:0]; // 8 registers of 8 bits each
    integer i;

    // Asynchronous read with artificial delay using continuous assignment
    assign #2 OUT1 = registers[OUT1ADDRESS];
    assign #2 OUT2 = registers[OUT2ADDRESS];

    // Synchronous Write and Reset with artificial delay
    always @(posedge CLK) begin
        if (RESET == 1'b1) begin
            #1 for (i = 0; i < 8; i = i + 1) begin
                 registers[i] = 8'b0;     // Clear all registers
            end
        end else if (WRITE == 1'b1) begin
            #1 registers[INADDRESS] = IN;   // Write data with delay
        end
    end

    initial 
    begin
        //$monitor($time, "\t%d\t%d\t%d\t%d\t%d\t%d\t%d\t%d", REGISTERFILES[0], REGISTERFILES[1],REGISTERFILES[2],REGISTERFILES[3],REGISTERFILES[4],REGISTERFILES[5],REGISTERFILES[6],REGISTERFILES[7]);
		$monitor($time, "\t%d\t%d", OUT1,OUT2);
	end

endmodule

Part3_Integration/cpuTestBench.v
module cpu_tb;

    reg CLK, RESET;
    wire [31:0] PC;
    wire [31:0] INSTRUCTION;

    //Initialize an array of registers (8x1024) named 'instr_mem' to be used as instruction memory
	reg [7:0] instr_mem [1023:0];
    
    //Create combinational logic to support CPU instruction fetching, given the Program Counter(PC) value 
    //       (make sure you include the delay for instruction fetching here)
	assign #2 INSTRUCTION = {instr_mem[PC+3], instr_mem[PC+2], instr_mem[PC+1], instr_mem[PC]};
    
    initial
    begin
        // Initialize instruction memory with the set of instructions you need execute on CPU
        
        // METHOD 1: manually loading instructions to instr_mem
        // loadi R4, 5
        {instr_mem[3], instr_mem[2], instr_mem[1], instr_mem[0]} = 32'b00000000_00000100_00000000_00000101;

        // loadi R2, 5
        {instr_mem[7], instr_mem[6], instr_mem[5], instr_mem[4]} = 32'b00000000_00000010_00000000_00000101;

        // add R6, R4, R2
        {instr_mem[11], instr_mem[10], instr_mem[9], instr_mem[8]} = 32'b00000010_00000110_00000100_00000010;

        // mov R1, R4
        {instr_mem[15], instr_mem[14], instr_mem[13], instr_mem[12]} = 32'b00000001_00000001_00000100_00000000;

        // sub R3, R6, R2
        {instr_mem[19], instr_mem[18], instr_mem[17], instr_mem[16]} = 32'b00000011_00000011_00000110_00000010;

        // and R7, R4, R2
        {instr_mem[23], instr_mem[22], instr_mem[21], instr_mem[20]} = 32'b00000100_00000111_00000100_00000010;

        // or R5, R4, R2
        {instr_mem[27], instr_mem[26], instr_mem[25], instr_mem[24]} = 32'b00000101_00000101_00000100_00000010;
        
        // METHOD 2: loading instr_mem content from instr_mem.mem file
        // $readmemb("instr_mem.mem", instr_mem);
    end
    
    cpu mycpu(PC, INSTRUCTION, CLK, RESET);

    initial
    begin
    
        // generate files needed to plot the waveform using GTKWave
        $dumpfile("cpu_wavedata.vcd");
		$dumpvars(0, cpu_tb);
        
        CLK = 1'b0;
        RESET = 1'b0;
        
        //Reset the CPU (by giving a pulse to RESET signal) to start the program execution
		RESET = 1'b1;
		#5
		RESET = 1'b0;
        
        // finish simulation after some time
        #500
        $finish;
        
    end
    
    // clock signal generation
    always
        #4 CLK = ~CLK;
        

endmodule

Part3_Integration/cpu_wavedata.vcd
$date
	Mon May 26 21:56:49 2025
$end
$version
	Icarus Verilog
$end
$timescale
	1s
$end
$scope module cpu_tb $end
$var wire 32 ! PC [31:0] $end
$var wire 32 " INSTRUCTION [31:0] $end
$var reg 1 # CLK $end
$var reg 1 $ RESET $end
$scope module mycpu $end
$var wire 1 # CLK $end
$var wire 32 % INSTRUCTION [31:0] $end
$var wire 1 $ RESET $end
$var wire 8 & registerOp [7:0] $end
$var wire 8 ' negatedOp [7:0] $end
$var wire 3 ( WRITEREG [2:0] $end
$var wire 8 ) REGOUT2 [7:0] $end
$var wire 8 * REGOUT1 [7:0] $end
$var wire 3 + READREG2 [2:0] $end
$var wire 3 , READREG1 [2:0] $end
$var wire 8 - OPERAND2 [7:0] $end
$var wire 8 . IMMEDIATE [7:0] $end
$var wire 8 / ALURESULT [7:0] $end
$var reg 3 0 ALUOP [2:0] $end
$var reg 8 1 OPCODE [7:0] $end
$var reg 32 2 PC [31:0] $end
$var reg 32 3 PCreg [31:0] $end
$var reg 1 4 WRITEENABLE $end
$var reg 1 5 immSelect $end
$var reg 1 6 signSelect $end
$scope module immediateMUX $end
$var wire 8 7 IN2 [7:0] $end
$var wire 1 5 SELECT $end
$var wire 8 8 IN1 [7:0] $end
$var reg 8 9 OUT [7:0] $end
$upscope $end
$scope module my_alu $end
$var wire 8 : DATA2 [7:0] $end
$var wire 3 ; SELECT [2:0] $end
$var wire 8 < orResult [7:0] $end
$var wire 8 = forwardResult [7:0] $end
$var wire 8 > andResult [7:0] $end
$var wire 8 ? addResult [7:0] $end
$var wire 8 @ DATA1 [7:0] $end
$var reg 8 A RESULT [7:0] $end
$scope module addModuleAlu $end
$var wire 8 B DATA2 [7:0] $end
$var wire 8 C DATA1 [7:0] $end
$var reg 8 D addResult [7:0] $end
$upscope $end
$scope module andModuleAlu $end
$var wire 8 E DATA2 [7:0] $end
$var wire 8 F DATA1 [7:0] $end
$var reg 8 G andResult [7:0] $end
$upscope $end
$scope module forwardModuleAlu $end
$var wire 8 H DATA2 [7:0] $end
$var wire 8 I DATA1 [7:0] $end
$var reg 8 J forwardResult [7:0] $end
$upscope $end
$scope module orModuleAlu $end
$var wire 8 K DATA2 [7:0] $end
$var wire 8 L DATA1 [7:0] $end
$var reg 8 M orResult [7:0] $end
$upscope $end
$upscope $end
$scope module my_reg $end
$var wire 1 # CLK $end
$var wire 8 N IN [7:0] $end
$var wire 3 O INADDRESS [2:0] $end
$var wire 8 P OUT1 [7:0] $end
$var wire 3 Q OUT1ADDRESS [2:0] $end
$var wire 8 R OUT2 [7:0] $end
$var wire 3 S OUT2ADDRESS [2:0] $end
$var wire 1 $ RESET $end
$var wire 1 4 WRITE $end
$var integer 32 T i [31:0] $end
$upscope $end
$scope module my_twosComp $end
$var wire 8 U IN [7:0] $end
$var wire 8 V OUT [7:0] $end
$upscope $end
$scope module negationMUX $end
$var wire 8 W IN1 [7:0] $end
$var wire 8 X IN2 [7:0] $end
$var wire 1 6 SELECT $end
$var reg 8 Y OUT [7:0] $end
$upscope $end
$upscope $end
$upscope $end
$enddefinitions $end
$comment Show the parameter values. $end
$dumpall
$end
#0
$dumpvars
bx Y
bx X
bx W
bx V
bx U
bx T
bx S
bx R
bx Q
bx P
bx O
bx N
bx M
bx L
bx K
bx J
bx I
bx H
bx G
bx F
bx E
bx D
bx C
bx B
bx A
bx @
bx ?
bx >
bx =
bx <
bx ;
bx :
bx 9
bx 8
bx 7
x6
x5
x4
bx 3
bx 2
bx 1
bx 0
bx /
bx .
bx -
bx ,
bx +
bx *
bx )
bx (
bx '
bx &
bx %
1$
0#
bx "
bx !
$end
#4
1#
#5
b1000 T
b0 3
b0 !
b0 2
0$
#6
b100 3
#7
b0 ,
b0 Q
b101 +
b101 S
b100 (
b100 O
b0 1
b101 .
b101 7
b1000000000000000101 "
b1000000000000000101 %
#8
b101 -
b101 9
b101 :
b101 B
b101 E
b101 H
b101 K
14
06
15
b0 0
b0 ;
0#
#9
b101 /
b101 A
b101 N
b0 &
b0 8
b0 Y
b101 =
b101 J
b101 <
b101 M
b0 >
b0 G
b0 *
b0 @
b0 C
b0 F
b0 I
b0 L
b0 P
b0 )
b0 R
b0 U
b0 W
#10
b0 '
b0 V
b0 X
b101 ?
b101 D
#12
1#
#13
b100 !
b100 2
#14
b1000 3
#15
b10 (
b10 O
b100000000000000101 "
b100000000000000101 %
#16
0#
#20
1#
#21
b1000 !
b1000 2
#22
b1100 3
#23
b100 ,
b100 Q
b10 -
b10 9
b10 :
b10 B
b10 E
b10 H
b10 K
b10 +
b10 S
b110 (
b110 O
b10 1
b10 .
b10 7
b10000001100000010000000010 "
b10000001100000010000000010 %
#24
b0 -
b0 9
b0 :
b0 B
b0 E
b0 H
b0 K
b10 <
b10 M
b10 =
b10 J
05
b1 0
b1 ;
0#
#25
b101 -
b101 9
b101 :
b101 B
b101 E
b101 H
b101 K
b101 &
b101 8
b101 Y
b0 =
b0 J
b101 <
b101 M
b101 *
b101 @
b101 C
b101 F
b101 I
b101 L
b101 P
b101 )
b101 R
b101 U
b101 W
#26
b101 >
b101 G
b101 =
b101 J
b11111011 '
b11111011 V
b11111011 X
#27
b1010 /
b1010 A
b1010 N
b1010 ?
b1010 D
#28
1#
#29
b1100 !
b1100 2
#30
b10000 3
#31
b0 +
b0 S
b1 (
b1 O
b1 1
b0 .
b0 7
b1000000010000010000000000 "
b1000000010000010000000000 %
#32
b101 /
b101 A
b101 N
b0 0
b0 ;
0#
#33
b0 -
b0 9
b0 :
b0 B
b0 E
b0 H
b0 K
b0 &
b0 8
b0 Y
b0 )
b0 R
b0 U
b0 W
#34
b0 /
b0 A
b0 N
b0 =
b0 J
b0 >
b0 G
b0 '
b0 V
b0 X
#35
b101 ?
b101 D
#36
1#
#37
b10000 !
b10000 2
#38
b10100 3
#39
b110 ,
b110 Q
b10 +
b10 S
b11 (
b11 O
b11 1
b10 .
b10 7
b11000000110000011000000010 "
b11000000110000011000000010 %
#40
b101 /
b101 A
b101 N
16
b1 0
b1 ;
0#
#41
b1010 *
b1010 @
b1010 C
b1010 F
b1010 I
b1010 L
b1010 P
b101 )
b101 R
b101 U
b101 W
#42
b11111011 -
b11111011 9
b11111011 :
b11111011 B
b11111011 E
b11111011 H
b11111011 K
b11111011 &
b11111011 8
b11111011 Y
b1010 <
b1010 M
b11111011 '
b11111011 V
b11111011 X
#43
b11111011 =
b11111011 J
b11111011 <
b11111011 M
b1010 >
b1010 G
#44
1#
#45
b10100 !
b10100 2
#46
b11000 3
#47
b100 ,
b100 Q
b111 (
b111 O
b100 1
b100000001110000010000000010 "
b100000001110000010000000010 %
#48
b101 -
b101 9
b101 :
b101 B
b101 E
b101 H
b101 K
b101 &
b101 8
b101 Y
b1010 /
b1010 A
b1010 N
06
b10 0
b10 ;
0#
#49
b101 /
b101 A
b101 N
b101 >
b101 G
b101 <
b101 M
b101 =
b101 J
b101 *
b101 @
b101 C
b101 F
b101 I
b101 L
b101 P
#50
b1010 ?
b1010 D
#52
1#
#53
b11000 !
b11000 2
#54
b11100 3
#55
b101 (
b101 O
b101 1
b101000001010000010000000010 "
b101000001010000010000000010 %
#56
b11 0
b11 ;
0#
#60
1#
#61
b11100 !
b11100 2
#62
b100000 3
#63
bx ,
bx Q
bx +
bx S
bx (
bx O
bx 1
bx .
bx 7
bx "
bx %
#64
0#
#65
bx -
bx 9
bx :
bx B
bx E
bx H
bx K
bx &
bx 8
bx Y
bx *
bx @
bx C
bx F
bx I
bx L
bx P
bx )
bx R
bx U
bx W
#66
bx /
bx A
bx N
bx =
bx J
bx <
bx M
bx >
bx G
bx '
bx V
bx X
#67
bx ?
bx D
#68
1#
#69
b100000 !
b100000 2
#70
b100100 3
#72
0#
#76
1#
#77
b100100 !
b100100 2
#78
b101000 3
#80
0#
#84
1#
#85
b101000 !
b101000 2
#86
b101100 3
#88
0#
#92
1#
#93
b101100 !
b101100 2
#94
b110000 3
#96
0#
#100
1#
#101
b110000 !
b110000 2
#102
b110100 3
#104
0#
#108
1#
#109
b110100 !
b110100 2
#110
b111000 3
#112
0#
#116
1#
#117
b111000 !
b111000 2
#118
b111100 3
#120
0#
#124
1#
#125
b111100 !
b111100 2
#126
b1000000 3
#128
0#
#132
1#
#133
b1000000 !
b1000000 2
#134
b1000100 3
#136
0#
#140
1#
#141
b1000100 !
b1000100 2
#142
b1001000 3
#144
0#
#148
1#
#149
b1001000 !
b1001000 2
#150
b1001100 3
#152
0#
#156
1#
#157
b1001100 !
b1001100 2
#158
b1010000 3
#160
0#
#164
1#
#165
b1010000 !
b1010000 2
#166
b1010100 3
#168
0#
#172
1#
#173
b1010100 !
b1010100 2
#174
b1011000 3
#176
0#
#180
1#
#181
b1011000 !
b1011000 2
#182
b1011100 3
#184
0#
#188
1#
#189
b1011100 !
b1011100 2
#190
b1100000 3
#192
0#
#196
1#
#197
b1100000 !
b1100000 2
#198
b1100100 3
#200
0#
#204
1#
#205
b1100100 !
b1100100 2
#206
b1101000 3
#208
0#
#212
1#
#213
b1101000 !
b1101000 2
#214
b1101100 3
#216
0#
#220
1#
#221
b1101100 !
b1101100 2
#222
b1110000 3
#224
0#
#228
1#
#229
b1110000 !
b1110000 2
#230
b1110100 3
#232
0#
#236
1#
#237
b1110100 !
b1110100 2
#238
b1111000 3
#240
0#
#244
1#
#245
b1111000 !
b1111000 2
#246
b1111100 3
#248
0#
#252
1#
#253
b1111100 !
b1111100 2
#254
b10000000 3
#256
0#
#260
1#
#261
b10000000 !
b10000000 2
#262
b10000100 3
#264
0#
#268
1#
#269
b10000100 !
b10000100 2
#270
b10001000 3
#272
0#
#276
1#
#277
b10001000 !
b10001000 2
#278
b10001100 3
#280
0#
#284
1#
#285
b10001100 !
b10001100 2
#286
b10010000 3
#288
0#
#292
1#
#293
b10010000 !
b10010000 2
#294
b10010100 3
#296
0#
#300
1#
#301
b10010100 !
b10010100 2
#302
b10011000 3
#304
0#
#308
1#
#309
b10011000 !
b10011000 2
#310
b10011100 3
#312
0#
#316
1#
#317
b10011100 !
b10011100 2
#318
b10100000 3
#320
0#
#324
1#
#325
b10100000 !
b10100000 2
#326
b10100100 3
#328
0#
#332
1#
#333
b10100100 !
b10100100 2
#334
b10101000 3
#336
0#
#340
1#
#341
b10101000 !
b10101000 2
#342
b10101100 3
#344
0#
#348
1#
#349
b10101100 !
b10101100 2
#350
b10110000 3
#352
0#
#356
1#
#357
b10110000 !
b10110000 2
#358
b10110100 3
#360
0#
#364
1#
#365
b10110100 !
b10110100 2
#366
b10111000 3
#368
0#
#372
1#
#373
b10111000 !
b10111000 2
#374
b10111100 3
#376
0#
#380
1#
#381
b10111100 !
b10111100 2
#382
b11000000 3
#384
0#
#388
1#
#389
b11000000 !
b11000000 2
#390
b11000100 3
#392
0#
#396
1#
#397
b11000100 !
b11000100 2
#398
b11001000 3
#400
0#
#404
1#
#405
b11001000 !
b11001000 2
#406
b11001100 3
#408
0#
#412
1#
#413
b11001100 !
b11001100 2
#414
b11010000 3
#416
0#
#420
1#
#421
b11010000 !
b11010000 2
#422
b11010100 3
#424
0#
#428
1#
#429
b11010100 !
b11010100 2
#430
b11011000 3
#432
0#
#436
1#
#437
b11011000 !
b11011000 2
#438
b11011100 3
#440
0#
#444
1#
#445
b11011100 !
b11011100 2
#446
b11100000 3
#448
0#
#452
1#
#453
b11100000 !
b11100000 2
#454
b11100100 3
#456
0#
#460
1#
#461
b11100100 !
b11100100 2
#462
b11101000 3
#464
0#
#468
1#
#469
b11101000 !
b11101000 2
#470
b11101100 3
#472
0#
#476
1#
#477
b11101100 !
b11101100 2
#478
b11110000 3
#480
0#
#484
1#
#485
b11110000 !
b11110000 2
#486
b11110100 3
#488
0#
#492
1#
#493
b11110100 !
b11110100 2
#494
b11111000 3
#496
0#
#500
1#
#501
b11111000 !
b11111000 2
#502
b11111100 3
