Part2_Reg/reg.v
module reg_file (
    IN,OUT1,OUT2,INADDRESS,OUT1ADDRESS,OUT2ADDRESS, WRITE, CLK, RESET
);
    input [7:0] IN;
    input [2:0] INADDRESS, OUT1ADDRESS, OUT2ADDRESS;
    input WRITE, CLK, RESET;
    output reg [7:0] OUT1, OUT2;

    reg [7:0] registers [7:0]; // 8 registers of 8 bits each
    integer i;

    // Asynchronous read with artificial delay
    always @(*) begin
        #2 OUT1 = registers[OUT1ADDRESS];
    end

    always @(*) begin
        #2 OUT2 = registers[OUT2ADDRESS];
    end


    // Synchronous Write and Reset with artificial delay
    always @(posedge CLK) begin
        if (RESET) begin
            for (i = 0; i < 8; i = i + 1) begin
                #1 registers[i] = 8'b0;     // Clear all registers
            end
        end else if (WRITE) begin
            #1 registers[INADDRESS] = IN;   // Write data with delay
        end
    end

endmodule

Part2_Reg/regTestbench.v
module regTestbench;

    // Inputs
    reg [7:0] IN;
    reg [2:0] INADDRESS, OUT1ADDRESS, OUT2ADDRESS;
    reg WRITE, CLK, RESET;

    // Outputs
    wire [7:0] OUT1, OUT2;

    // Instantiate the reg_file
    reg_file uut (
        .IN(IN),
        .INADDRESS(INADDRESS),
        .OUT1ADDRESS(OUT1ADDRESS),
        .OUT2ADDRESS(OUT2ADDRESS),
        .WRITE(WRITE),
        .CLK(CLK),
        .RESET(RESET),
        .OUT1(OUT1),
        .OUT2(OUT2)
    );

    // Clock Generation: 10ns period (100 MHz)
    initial CLK = 0;
    always #5 CLK = ~CLK;

    // Simulation
    initial begin
        $dumpfile("reg_file_tb.vcd"); // For GTKWave
        $dumpvars(0, regTestbench);

        // Initial values
        IN = 8'b0;
        INADDRESS = 3'b000;
        OUT1ADDRESS = 3'b000;
        OUT2ADDRESS = 3'b001;
        WRITE = 0;
        RESET = 0;

        // Wait a bit before starting
        #2;

        // --- Reset all registers ---
        RESET = 1;
        #10; // Wait for rising edge
        RESET = 0;
        #10;

        // --- Write 55h to register 3 ---
        IN = 8'h55;
        INADDRESS = 3'b011;
        WRITE = 1;
        #10; // Rising edge of CLK
        WRITE = 0;
        #10;

        // --- Write AAh to register 5 ---
        IN = 8'hAA;
        INADDRESS = 3'b101;
        WRITE = 1;
        #10;
        WRITE = 0;
        #10;

        // --- Read from registers 3 and 5 ---
        OUT1ADDRESS = 3'b011;
        OUT2ADDRESS = 3'b101;
        #5; // allow #2 delay for OUT1 and OUT2
        $display("OUT1 (Reg 3): %h | OUT2 (Reg 5): %h", OUT1, OUT2);

        // --- Change read addresses ---
        OUT1ADDRESS = 3'b000; // Should be 0 (after reset)
        OUT2ADDRESS = 3'b100; // Also 0
        #5;
        $display("OUT1 (Reg 0): %h | OUT2 (Reg 4): %h", OUT1, OUT2);

        // --- Reset again and check all are 0 ---
        RESET = 1;
        #10;
        RESET = 0;
        #10;
        OUT1ADDRESS = 3'b011; // Previously written
        OUT2ADDRESS = 3'b101; // Previously written
        #5;
        $display("After reset - OUT1: %h | OUT2: %h", OUT1, OUT2);

        // End simulation
        #20;
        $finish;
    end

endmodule

Part2_Reg/reg_file_tb.vcd
$date
	Mon May 26 00:25:43 2025
$end
$version
	Icarus Verilog
$end
$timescale
	1s
$end
$scope module regTestbench $end
$var wire 8 ! OUT2 [7:0] $end
$var wire 8 " OUT1 [7:0] $end
$var reg 1 # CLK $end
$var reg 8 $ IN [7:0] $end
$var reg 3 % INADDRESS [2:0] $end
$var reg 3 & OUT1ADDRESS [2:0] $end
$var reg 3 ' OUT2ADDRESS [2:0] $end
$var reg 1 ( RESET $end
$var reg 1 ) WRITE $end
$scope module uut $end
$var wire 1 # CLK $end
$var wire 8 * IN [7:0] $end
$var wire 3 + INADDRESS [2:0] $end
$var wire 3 , OUT1ADDRESS [2:0] $end
$var wire 3 - OUT2ADDRESS [2:0] $end
$var wire 1 ( RESET $end
$var wire 1 ) WRITE $end
$var reg 8 . OUT1 [7:0] $end
$var reg 8 / OUT2 [7:0] $end
$var integer 32 0 i [31:0] $end
$upscope $end
$upscope $end
$enddefinitions $end
$comment Show the parameter values. $end
$dumpall
$end
#0
$dumpvars
bx 0
bx /
bx .
b1 -
b0 ,
b0 +
b0 *
0)
0(
b1 '
b0 &
b0 %
b0 $
0#
bx "
bx !
$end
#2
1(
#5
b0 0
1#
#6
b1 0
#7
b10 0
#8
b11 0
b0 !
b0 /
b0 "
b0 .
#9
b100 0
#10
b101 0
0#
#11
b110 0
#12
b111 0
0(
#13
b1000 0
#15
1#
#20
0#
#22
1)
b11 %
b11 +
b1010101 $
b1010101 *
#25
1#
#30
0#
#32
0)
#35
1#
#40
0#
#42
1)
b101 %
b101 +
b10101010 $
b10101010 *
#45
1#
#50
0#
#52
0)
#55
1#
#60
0#
#62
b101 '
b101 -
b11 &
b11 ,
#64
b10101010 !
b10101010 /
b1010101 "
b1010101 .
#65
1#
#67
b100 '
b100 -
b0 &
b0 ,
#69
b0 !
b0 /
b0 "
b0 .
#70
0#
#72
1(
#75
b0 0
1#
#76
b1 0
#77
b10 0
#78
b11 0
#79
b100 0
#80
b101 0
0#
#81
b110 0
#82
b111 0
0(
#83
b1000 0
#85
1#
#90
0#
#92
b101 '
b101 -
b11 &
b11 ,
