Part2_Reg/reg.v
module reg_file (
    IN,OUT1,OUT2,INADDRESS,OUT1ADDRESS,OUT2ADDRESS, WRITE, CLK, RESET
);
    input [7:0] IN;
    input [2:0] INADDRESS, OUT1ADDRESS, OUT2ADDRESS;
    input WRITE, CLK, RESET;
    output reg [7:0] OUT1, OUT2;

    reg [7:0] registers [7:0]; // 8 registers of 8 bits each
    integer i;

    // Asynchronous Read with artificial delay
    always @(*) begin
        #2 OUT1 = registers[OUT1ADDRESS];
        #2 OUT2 = registers[OUT2ADDRESS];
    end

    // Synchronous Write and Reset with artificial delay
    always @(posedge CLK) begin
        if (RESET) begin
            for (i = 0; i < 8; i = i + 1) begin
                #1 registers[i] = 8'b0;     // Clear all registers
            end
        end else if (WRITE) begin
            #1 registers[INADDRESS] = IN;   // Write data with delay
        end
    end

endmodule

Part2_Reg/regTestbench.v
module reg_file_tb;

    reg [7:0] IN;
    wire [7:0] OUT1, OUT2;
    reg [2:0] INADDRESS, OUT1ADDRESS, OUT2ADDRESS;
    reg WRITE, CLK, RESET;

    // Instantiate the register file
    reg_file uut (
        .IN(IN),
        .OUT1(OUT1),
        .OUT2(OUT2),
        .INADDRESS(INADDRESS),
        .OUT1ADDRESS(OUT1ADDRESS),
        .OUT2ADDRESS(OUT2ADDRESS),
        .WRITE(WRITE),
        .CLK(CLK),
        .RESET(RESET)
    );

    // Clock generation: 10ns period
    initial CLK = 0;
    always #5 CLK = ~CLK;

    initial begin
        // Initialize inputs
        IN = 8'b0;
        INADDRESS = 3'b0;
        OUT1ADDRESS = 3'b0;
        OUT2ADDRESS = 3'b0;
        WRITE = 0;
        RESET = 0;

        // Dump waves for GTKWave
        $dumpfile("reg_file_tb.vcd");
        $dumpvars(0, reg_file_tb);

        // Reset the register file
        @(negedge CLK);
        RESET = 1;
        @(posedge CLK);
        RESET = 0;

        // Wait a few cycles for reset to complete
        repeat (3) @(posedge CLK);

        // Write some values
        IN = 8'hAA; INADDRESS = 3'd1; WRITE = 1;
        @(posedge CLK);
        WRITE = 0;
        @(posedge CLK);

        IN = 8'h55; INADDRESS = 3'd3; WRITE = 1;
        @(posedge CLK);
        WRITE = 0;
        @(posedge CLK);

        IN = 8'hFF; INADDRESS = 3'd5; WRITE = 1;
        @(posedge CLK);
        WRITE = 0;
        @(posedge CLK);

        // Read back values asynchronously by setting OUT addresses
        OUT1ADDRESS = 3'd1;
        OUT2ADDRESS = 3'd3;
        #10;  // Wait to observe delayed asynchronous read

        $display("OUT1 (reg 1) = %h, OUT2 (reg 3) = %h", OUT1, OUT2);


        OUT1ADDRESS = 3'd5;
        OUT2ADDRESS = 3'd0;
        #10;

        $display("OUT1 (reg 5) = %h, OUT2 (reg 0) = %h", OUT1, OUT2);

        // Test reset again
        @(negedge CLK);
        RESET = 1;
        @(posedge CLK);
        RESET = 0;
        #10;

        $display("After reset: OUT1 (reg 1) = %h, OUT2 (reg 3) = %h", OUT1, OUT2);

        $finish;
    end

endmodule

Part2_Reg/reg_file_tb.vcd
$date
	Wed May 21 08:08:39 2025
$end
$version
	Icarus Verilog
$end
$timescale
	1s
$end
$scope module reg_file_tb $end
$var wire 8 ! OUT2 [7:0] $end
$var wire 8 " OUT1 [7:0] $end
$var reg 1 # CLK $end
$var reg 8 $ IN [7:0] $end
$var reg 3 % INADDRESS [2:0] $end
$var reg 3 & OUT1ADDRESS [2:0] $end
$var reg 3 ' OUT2ADDRESS [2:0] $end
$var reg 1 ( RESET $end
$var reg 1 ) WRITE $end
$scope module uut $end
$var wire 1 # CLK $end
$var wire 8 * IN [7:0] $end
$var wire 3 + INADDRESS [2:0] $end
$var wire 3 , OUT1ADDRESS [2:0] $end
$var wire 3 - OUT2ADDRESS [2:0] $end
$var wire 1 ( RESET $end
$var wire 1 ) WRITE $end
$var reg 8 . OUT1 [7:0] $end
$var reg 8 / OUT2 [7:0] $end
$var integer 32 0 i [31:0] $end
$upscope $end
$upscope $end
$enddefinitions $end
$comment Show the parameter values. $end
$dumpall
$end
#0
$dumpvars
bx 0
bx /
bx .
b0 -
b0 ,
b0 +
b0 *
0)
0(
b0 '
b0 &
b0 %
b0 $
0#
bx "
bx !
$end
#5
1#
#10
1(
0#
#15
0(
1#
#20
0#
#25
1#
#30
0#
#35
1#
#40
0#
#45
1)
b1 %
b1 +
b10101010 $
b10101010 *
1#
#50
0#
#55
0)
1#
#60
0#
#65
1)
b11 %
b11 +
b1010101 $
b1010101 *
1#
#70
0#
#75
0)
1#
#80
0#
#85
1)
b101 %
b101 +
b11111111 $
b11111111 *
1#
#90
0#
#95
0)
1#
#100
0#
#105
b11 '
b11 -
b1 &
b1 ,
1#
#110
0#
#115
1#
b0 '
b0 -
b101 &
b101 ,
#120
0#
#125
1#
#130
1(
0#
#135
0(
1#
